memento/__init__.py
memento/cli.py
memento/crud.py
memento/models.py
memento/recorder.py
memento_llm-0.3.3.dist-info/LICENSE
memento_llm-0.3.3.dist-info/METADATA
memento_llm-0.3.3.dist-info/WHEEL
memento_llm-0.3.3.dist-info/entry_points.txt
memento_llm-0.3.3.dist-info/RECORD
