Metadata-Version: 2.1
Name: memento-llm
Version: 0.3.3
Summary: Simple LLM Memory
Author: Anibal Angulo
Author-email: ajcardoza2000@gmail.com
Requires-Python: >=3.9,<4.0
Classifier: Programming Language :: Python :: 3
Classifier: Programming Language :: Python :: 3.9
Classifier: Programming Language :: Python :: 3.10
Classifier: Programming Language :: Python :: 3.11
Classifier: Programming Language :: Python :: 3.12
Requires-Dist: click (>=8.1.7,<9.0.0)
Requires-Dist: rich (>=13.9.4,<14.0.0)
Requires-Dist: sqlalchemy[asyncio] (>=2.0.36,<3.0.0)
